docker_optimizer
test
